{
  "name": "mpv-bash-completion",
  "tagline": "Bash completion for the mpv video player · Linux/BSD/OSX",
  "body": "A script for generating a Bash completion script for the popular [mpv\r\nvideo player](https://github.com/mpv-player/mpv).\r\nIt features...\r\n\r\n* Completion for all --options,\r\n* Type-based completion for --option arguments for choices, flags,\r\n  integers and floats,\r\n* Completion for upper/lower bounds for integer- and float-type argument\r\n  ranges where applicable,\r\n* Regular file name completion.\r\n\r\nIt does so by parsing the output of\r\n```\r\nmpv --list-options\r\n```\r\ndirectly and should thus work against all recent versions of mpv, though\r\nthe only support version is the current mpv release.\r\n\r\nWe support build methods for the following platforms:\r\n\r\n* [Arch Linux](https://github.com/2ion/mpv-bash-completion#arch-linux)\r\n* [OSX Homebrew](https://github.com/2ion/mpv-bash-completion#osx-homebrew)\r\n* [Generic Linux/OSX/Unix](https://github.com/2ion/mpv-bash-completion#platform-agnostic-method)\r\n\r\n## Dependencies\r\n\r\n* Bash 4. OS X users must install an up-to-date Bash version using\r\n  homebrew, macports or similar.\r\n* Lua 5.1, 5.2 or 5.3 as well as LuaJIT\r\n* mpv\r\n\r\n## Usage\r\n\r\nYou can just generate the completion script or build a package for one\r\nof the supported platforms.\r\n\r\n### Platform-agnostic method\r\n\r\nJust execute\r\n```sh\r\n# You may set the following environment variables beforehand:\r\n# export MPV_BASHCOMPGEN_VERBOSE=1 # verbose debug/progress output\r\n# export MPV_BASHCOMPGEN_MPV_CMD=mpv # path or command to execute mpv, defaults to 'mpv'\r\n# export MPV_BASHCOMPGEN_VERBOSE=foo # override version tag in the output file\r\n\r\n./gen.lua > mpv.sh\r\n```\r\nand source the resulting file into Bash.\r\n\r\n### Arch Linux\r\n\r\nInstall [mpv-bash-completion-git](https://aur.archlinux.org/packages/mpv-bash-completion-git/)\r\nfrom the AUR. It will install all necessary dependencies and also ships\r\na pacman hook which automatically rebuilds the completion file whenever\r\nyou update mpv so it's **not** necessary to install the package every time.\r\n\r\nThe PKGBUILD lives on the `aur4` branch.\r\n\r\n### OSX Homebrew\r\n\r\nYou can simply install using the provided formula. You need to reinstall\r\nevery time you upgrade mpv in order to update the completion function to\r\nmatch the current mpv build.\r\n\r\n```sh\r\nbrew tap 2ion/mpv-bash-completion https://github.com/2ion/mpv-bash-completion.git\r\nbrew install --HEAD mpv-bash-completion\r\n```\r\n",
  "google": "",
  "note": "Don't delete this file! It's used internally to help with page regeneration."
}